[
 {
  "default_value": null,
  "doc_type": "Employee",
  "docstatus": 0,
  "doctype": "Property Setter",
  "doctype_or_field": "DocField",
  "field_name": "naming_series",
  "modified": "2022-07-19 11:58:42.367738",
  "name": "Employee-naming_series-options",
  "parent": null,
  "parentfield": null,
  "parenttype": null,
  "property": "options",
  "property_type": "Text",
  "row_name": null,
  "value": "HR-EMP-\nEK\nEL\nEA\nEB\nE1\nE2.####\nE5\nE6\nE7"
 },
 {
  "default_value": null,
  "doc_type": "Employee",
  "docstatus": 0,
  "doctype": "Property Setter",
  "doctype_or_field": "DocField",
  "field_name": "naming_series",
  "modified": "2022-07-19 11:58:42.395100",
  "name": "Employee-naming_series-default",
  "parent": null,
  "parentfield": null,
  "parenttype": null,
  "property": "default",
  "property_type": "Text",
  "row_name": null,
  "value": "HR-EMP-"
 },
 {
  "default_value": null,
  "doc_type": "Employee Education",
  "docstatus": 0,
  "doctype": "Property Setter",
  "doctype_or_field": "DocField",
  "field_name": "class_per",
  "modified": "2022-05-31 15:01:39.818337",
  "name": "Employee Education-class_per-permlevel",
  "parent": null,
  "parentfield": null,
  "parenttype": null,
  "property": "permlevel",
  "property_type": "Int",
  "row_name": null,
  "value": "1"
 },
 {
  "default_value": null,
  "doc_type": "Employee Education",
  "docstatus": 0,
  "doctype": "Property Setter",
  "doctype_or_field": "DocField",
  "field_name": "maj_opt_subj",
  "modified": "2022-05-31 15:01:39.873342",
  "name": "Employee Education-maj_opt_subj-permlevel",
  "parent": null,
  "parentfield": null,
  "parenttype": null,
  "property": "permlevel",
  "property_type": "Int",
  "row_name": null,
  "value": "1"
 },
 {
  "default_value": null,
  "doc_type": "Employee Education",
  "docstatus": 0,
  "doctype": "Property Setter",
  "doctype_or_field": "DocField",
  "field_name": "school_univ",
  "modified": "2022-05-31 15:03:20.250593",
  "name": "Employee Education-school_univ-permlevel",
  "parent": null,
  "parentfield": null,
  "parenttype": null,
  "property": "permlevel",
  "property_type": "Int",
  "row_name": null,
  "value": "1"
 },
 {
  "default_value": null,
  "doc_type": "Employee Education",
  "docstatus": 0,
  "doctype": "Property Setter",
  "doctype_or_field": "DocField",
  "field_name": "qualification",
  "modified": "2022-05-31 15:03:20.289386",
  "name": "Employee Education-qualification-permlevel",
  "parent": null,
  "parentfield": null,
  "parenttype": null,
  "property": "permlevel",
  "property_type": "Int",
  "row_name": null,
  "value": "1"
 },
 {
  "default_value": null,
  "doc_type": "Employee Education",
  "docstatus": 0,
  "doctype": "Property Setter",
  "doctype_or_field": "DocField",
  "field_name": "level",
  "modified": "2022-05-31 15:03:20.317636",
  "name": "Employee Education-level-permlevel",
  "parent": null,
  "parentfield": null,
  "parenttype": null,
  "property": "permlevel",
  "property_type": "Int",
  "row_name": null,
  "value": "1"
 },
 {
  "default_value": null,
  "doc_type": "Employee Education",
  "docstatus": 0,
  "doctype": "Property Setter",
  "doctype_or_field": "DocField",
  "field_name": "year_of_passing",
  "modified": "2022-05-31 15:03:20.346802",
  "name": "Employee Education-year_of_passing-permlevel",
  "parent": null,
  "parentfield": null,
  "parenttype": null,
  "property": "permlevel",
  "property_type": "Int",
  "row_name": null,
  "value": "1"
 },
 {
  "default_value": null,
  "doc_type": "Employee",
  "docstatus": 0,
  "doctype": "Property Setter",
  "doctype_or_field": "DocField",
  "field_name": "branch",
  "modified": "2022-05-31 15:09:07.213289",
  "name": "Employee-branch-label",
  "parent": null,
  "parentfield": null,
  "parenttype": null,
  "property": "label",
  "property_type": "Data",
  "row_name": null,
  "value": "Branch / Location / Project Site"
 },
 {
  "default_value": null,
  "doc_type": "Employee External Work History",
  "docstatus": 0,
  "doctype": "Property Setter",
  "doctype_or_field": "DocField",
  "field_name": "company_name",
  "modified": "2022-05-31 15:43:00.425248",
  "name": "Employee External Work History-company_name-permlevel",
  "parent": null,
  "parentfield": null,
  "parenttype": null,
  "property": "permlevel",
  "property_type": "Int",
  "row_name": null,
  "value": "1"
 },
 {
  "default_value": null,
  "doc_type": "Employee External Work History",
  "docstatus": 0,
  "doctype": "Property Setter",
  "doctype_or_field": "DocField",
  "field_name": "designation",
  "modified": "2022-05-31 15:43:00.493139",
  "name": "Employee External Work History-designation-permlevel",
  "parent": null,
  "parentfield": null,
  "parenttype": null,
  "property": "permlevel",
  "property_type": "Int",
  "row_name": null,
  "value": "1"
 },
 {
  "default_value": null,
  "doc_type": "Employee External Work History",
  "docstatus": 0,
  "doctype": "Property Setter",
  "doctype_or_field": "DocField",
  "field_name": "salary",
  "modified": "2022-05-31 15:43:00.517674",
  "name": "Employee External Work History-salary-permlevel",
  "parent": null,
  "parentfield": null,
  "parenttype": null,
  "property": "permlevel",
  "property_type": "Int",
  "row_name": null,
  "value": "1"
 },
 {
  "default_value": null,
  "doc_type": "Employee External Work History",
  "docstatus": 0,
  "doctype": "Property Setter",
  "doctype_or_field": "DocField",
  "field_name": "address",
  "modified": "2022-05-31 15:43:00.549894",
  "name": "Employee External Work History-address-permlevel",
  "parent": null,
  "parentfield": null,
  "parenttype": null,
  "property": "permlevel",
  "property_type": "Int",
  "row_name": null,
  "value": "1"
 },
 {
  "default_value": null,
  "doc_type": "Employee External Work History",
  "docstatus": 0,
  "doctype": "Property Setter",
  "doctype_or_field": "DocField",
  "field_name": "contact",
  "modified": "2022-05-31 15:43:00.575306",
  "name": "Employee External Work History-contact-permlevel",
  "parent": null,
  "parentfield": null,
  "parenttype": null,
  "property": "permlevel",
  "property_type": "Int",
  "row_name": null,
  "value": "1"
 },
 {
  "default_value": null,
  "doc_type": "Employee External Work History",
  "docstatus": 0,
  "doctype": "Property Setter",
  "doctype_or_field": "DocField",
  "field_name": "total_experience",
  "modified": "2022-05-31 15:43:00.602106",
  "name": "Employee External Work History-total_experience-permlevel",
  "parent": null,
  "parentfield": null,
  "parenttype": null,
  "property": "permlevel",
  "property_type": "Int",
  "row_name": null,
  "value": "1"
 },
 {
  "default_value": null,
  "doc_type": "Employee Internal Work History",
  "docstatus": 0,
  "doctype": "Property Setter",
  "doctype_or_field": "DocField",
  "field_name": "designation",
  "modified": "2022-05-31 15:48:02.579235",
  "name": "Employee Internal Work History-designation-permlevel",
  "parent": null,
  "parentfield": null,
  "parenttype": null,
  "property": "permlevel",
  "property_type": "Int",
  "row_name": null,
  "value": "1"
 },
 {
  "default_value": null,
  "doc_type": "Employee Internal Work History",
  "docstatus": 0,
  "doctype": "Property Setter",
  "doctype_or_field": "DocField",
  "field_name": "from_date",
  "modified": "2022-05-31 15:48:02.630475",
  "name": "Employee Internal Work History-from_date-permlevel",
  "parent": null,
  "parentfield": null,
  "parenttype": null,
  "property": "permlevel",
  "property_type": "Int",
  "row_name": null,
  "value": "1"
 },
 {
  "default_value": null,
  "doc_type": "Employee Internal Work History",
  "docstatus": 0,
  "doctype": "Property Setter",
  "doctype_or_field": "DocField",
  "field_name": "to_date",
  "modified": "2022-05-31 15:48:02.663584",
  "name": "Employee Internal Work History-to_date-permlevel",
  "parent": null,
  "parentfield": null,
  "parenttype": null,
  "property": "permlevel",
  "property_type": "Int",
  "row_name": null,
  "value": "1"
 },
 {
  "default_value": null,
  "doc_type": "Employee Internal Work History",
  "docstatus": 0,
  "doctype": "Property Setter",
  "doctype_or_field": "DocField",
  "field_name": "branch",
  "modified": "2022-05-31 15:50:04.232001",
  "name": "Employee Internal Work History-branch-permlevel",
  "parent": null,
  "parentfield": null,
  "parenttype": null,
  "property": "permlevel",
  "property_type": "Int",
  "row_name": null,
  "value": "1"
 },
 {
  "default_value": null,
  "doc_type": "Employee Internal Work History",
  "docstatus": 0,
  "doctype": "Property Setter",
  "doctype_or_field": "DocField",
  "field_name": "department",
  "modified": "2022-05-31 15:50:04.270312",
  "name": "Employee Internal Work History-department-permlevel",
  "parent": null,
  "parentfield": null,
  "parenttype": null,
  "property": "permlevel",
  "property_type": "Int",
  "row_name": null,
  "value": "1"
 },
 {
  "default_value": null,
  "doc_type": "Employee",
  "docstatus": 0,
  "doctype": "Property Setter",
  "doctype_or_field": "DocField",
  "field_name": "erpnext_user",
  "modified": "2022-06-06 15:52:43.487850",
  "name": "Employee-erpnext_user-label",
  "parent": null,
  "parentfield": null,
  "parenttype": null,
  "property": "label",
  "property_type": "Data",
  "row_name": null,
  "value": "ERP User ID"
 },
 {
  "default_value": null,
  "doc_type": "Employee",
  "docstatus": 0,
  "doctype": "Property Setter",
  "doctype_or_field": "DocField",
  "field_name": "employee_number",
  "modified": "2022-07-19 11:33:31.417692",
  "name": "Employee-employee_number-default",
  "parent": null,
  "parentfield": null,
  "parenttype": null,
  "property": "default",
  "property_type": "Text",
  "row_name": null,
  "value": ""
 },
 {
  "default_value": null,
  "doc_type": "Budget",
  "docstatus": 0,
  "doctype": "Property Setter",
  "doctype_or_field": "DocField",
  "field_name": "budget_against",
  "modified": "2022-08-17 13:14:33.796966",
  "name": "Budget-budget_against-options",
  "parent": null,
  "parentfield": null,
  "parenttype": null,
  "property": "options",
  "property_type": "Text",
  "row_name": null,
  "value": "\nCost Center\nProject\nBranch"
 },
 {
  "default_value": null,
  "doc_type": "Employee",
  "docstatus": 0,
  "doctype": "Property Setter",
  "doctype_or_field": "DocField",
  "field_name": "naming_series",
  "modified": "2022-08-22 11:58:02.830786",
  "name": "Employee-naming_series-hidden",
  "parent": null,
  "parentfield": null,
  "parenttype": null,
  "property": "hidden",
  "property_type": "Check",
  "row_name": null,
  "value": "0"
 },
 {
  "default_value": null,
  "doc_type": "Employee",
  "docstatus": 0,
  "doctype": "Property Setter",
  "doctype_or_field": "DocField",
  "field_name": "naming_series",
  "modified": "2022-08-22 11:58:02.941145",
  "name": "Employee-naming_series-reqd",
  "parent": null,
  "parentfield": null,
  "parenttype": null,
  "property": "reqd",
  "property_type": "Check",
  "row_name": null,
  "value": "1"
 },
 {
  "default_value": null,
  "doc_type": "Employee",
  "docstatus": 0,
  "doctype": "Property Setter",
  "doctype_or_field": "DocField",
  "field_name": "employee_number",
  "modified": "2022-08-22 11:58:03.015229",
  "name": "Employee-employee_number-reqd",
  "parent": null,
  "parentfield": null,
  "parenttype": null,
  "property": "reqd",
  "property_type": "Check",
  "row_name": null,
  "value": "0"
 },
 {
  "default_value": null,
  "doc_type": "Employee",
  "docstatus": 0,
  "doctype": "Property Setter",
  "doctype_or_field": "DocField",
  "field_name": "employee_number",
  "modified": "2022-08-22 11:58:03.028012",
  "name": "Employee-employee_number-hidden",
  "parent": null,
  "parentfield": null,
  "parenttype": null,
  "property": "hidden",
  "property_type": "Check",
  "row_name": null,
  "value": "1"
 },
 {
  "default_value": null,
  "doc_type": "Sales Order",
  "docstatus": 0,
  "doctype": "Property Setter",
  "doctype_or_field": "DocField",
  "field_name": "due_date",
  "modified": "2022-10-12 17:35:16.058533",
  "name": "Sales Order-due_date-print_hide",
  "parent": null,
  "parentfield": null,
  "parenttype": null,
  "property": "print_hide",
  "property_type": "Check",
  "row_name": null,
  "value": "0"
 },
 {
  "default_value": null,
  "doc_type": "Sales Order",
  "docstatus": 0,
  "doctype": "Property Setter",
  "doctype_or_field": "DocField",
  "field_name": "payment_schedule",
  "modified": "2022-10-12 17:35:16.081600",
  "name": "Sales Order-payment_schedule-print_hide",
  "parent": null,
  "parentfield": null,
  "parenttype": null,
  "property": "print_hide",
  "property_type": "Check",
  "row_name": null,
  "value": "1"
 },
 {
  "default_value": null,
  "doc_type": "Sales Invoice",
  "docstatus": 0,
  "doctype": "Property Setter",
  "doctype_or_field": "DocField",
  "field_name": "due_date",
  "modified": "2022-10-12 17:35:16.095476",
  "name": "Sales Invoice-due_date-print_hide",
  "parent": null,
  "parentfield": null,
  "parenttype": null,
  "property": "print_hide",
  "property_type": "Check",
  "row_name": null,
  "value": "0"
 },
 {
  "default_value": null,
  "doc_type": "Sales Invoice",
  "docstatus": 0,
  "doctype": "Property Setter",
  "doctype_or_field": "DocField",
  "field_name": "payment_schedule",
  "modified": "2022-10-12 17:35:16.106757",
  "name": "Sales Invoice-payment_schedule-print_hide",
  "parent": null,
  "parentfield": null,
  "parenttype": null,
  "property": "print_hide",
  "property_type": "Check",
  "row_name": null,
  "value": "1"
 },
 {
  "default_value": null,
  "doc_type": "Purchase Order",
  "docstatus": 0,
  "doctype": "Property Setter",
  "doctype_or_field": "DocField",
  "field_name": "due_date",
  "modified": "2022-10-12 17:35:16.117940",
  "name": "Purchase Order-due_date-print_hide",
  "parent": null,
  "parentfield": null,
  "parenttype": null,
  "property": "print_hide",
  "property_type": "Check",
  "row_name": null,
  "value": "0"
 },
 {
  "default_value": null,
  "doc_type": "Purchase Order",
  "docstatus": 0,
  "doctype": "Property Setter",
  "doctype_or_field": "DocField",
  "field_name": "payment_schedule",
  "modified": "2022-10-12 17:35:16.128975",
  "name": "Purchase Order-payment_schedule-print_hide",
  "parent": null,
  "parentfield": null,
  "parenttype": null,
  "property": "print_hide",
  "property_type": "Check",
  "row_name": null,
  "value": "1"
 },
 {
  "default_value": null,
  "doc_type": "Purchase Invoice",
  "docstatus": 0,
  "doctype": "Property Setter",
  "doctype_or_field": "DocField",
  "field_name": "due_date",
  "modified": "2022-10-12 17:35:16.139891",
  "name": "Purchase Invoice-due_date-print_hide",
  "parent": null,
  "parentfield": null,
  "parenttype": null,
  "property": "print_hide",
  "property_type": "Check",
  "row_name": null,
  "value": "0"
 },
 {
  "default_value": null,
  "doc_type": "Purchase Invoice",
  "docstatus": 0,
  "doctype": "Property Setter",
  "doctype_or_field": "DocField",
  "field_name": "payment_schedule",
  "modified": "2022-10-12 17:35:16.152485",
  "name": "Purchase Invoice-payment_schedule-print_hide",
  "parent": null,
  "parentfield": null,
  "parenttype": null,
  "property": "print_hide",
  "property_type": "Check",
  "row_name": null,
  "value": "1"
 },
 {
  "default_value": null,
  "doc_type": "Sales Invoice Item",
  "docstatus": 0,
  "doctype": "Property Setter",
  "doctype_or_field": "DocField",
  "field_name": "discount_account",
  "modified": "2022-10-12 17:35:16.165647",
  "name": "Sales Invoice Item-discount_account-hidden",
  "parent": null,
  "parentfield": null,
  "parenttype": null,
  "property": "hidden",
  "property_type": "Check",
  "row_name": null,
  "value": "1"
 },
 {
  "default_value": null,
  "doc_type": "Sales Invoice Item",
  "docstatus": 0,
  "doctype": "Property Setter",
  "doctype_or_field": "DocField",
  "field_name": "discount_account",
  "modified": "2022-10-12 17:35:16.179049",
  "name": "Sales Invoice Item-discount_account-mandatory_depends_on",
  "parent": null,
  "parentfield": null,
  "parenttype": null,
  "property": "mandatory_depends_on",
  "property_type": "Code",
  "row_name": null,
  "value": ""
 },
 {
  "default_value": null,
  "doc_type": "Purchase Invoice Item",
  "docstatus": 0,
  "doctype": "Property Setter",
  "doctype_or_field": "DocField",
  "field_name": "discount_account",
  "modified": "2022-10-12 17:35:16.191664",
  "name": "Purchase Invoice Item-discount_account-hidden",
  "parent": null,
  "parentfield": null,
  "parenttype": null,
  "property": "hidden",
  "property_type": "Check",
  "row_name": null,
  "value": "1"
 },
 {
  "default_value": null,
  "doc_type": "Purchase Invoice Item",
  "docstatus": 0,
  "doctype": "Property Setter",
  "doctype_or_field": "DocField",
  "field_name": "discount_account",
  "modified": "2022-10-12 17:35:16.207544",
  "name": "Purchase Invoice Item-discount_account-mandatory_depends_on",
  "parent": null,
  "parentfield": null,
  "parenttype": null,
  "property": "mandatory_depends_on",
  "property_type": "Code",
  "row_name": null,
  "value": ""
 },
 {
  "default_value": null,
  "doc_type": "Sales Invoice",
  "docstatus": 0,
  "doctype": "Property Setter",
  "doctype_or_field": "DocField",
  "field_name": "additional_discount_account",
  "modified": "2022-10-12 17:35:16.255752",
  "name": "Sales Invoice-additional_discount_account-hidden",
  "parent": null,
  "parentfield": null,
  "parenttype": null,
  "property": "hidden",
  "property_type": "Check",
  "row_name": null,
  "value": "1"
 },
 {
  "default_value": null,
  "doc_type": "Sales Invoice",
  "docstatus": 0,
  "doctype": "Property Setter",
  "doctype_or_field": "DocField",
  "field_name": "additional_discount_account",
  "modified": "2022-10-12 17:35:16.266338",
  "name": "Sales Invoice-additional_discount_account-mandatory_depends_on",
  "parent": null,
  "parentfield": null,
  "parenttype": null,
  "property": "mandatory_depends_on",
  "property_type": "Code",
  "row_name": null,
  "value": ""
 },
 {
  "default_value": null,
  "doc_type": "Purchase Invoice",
  "docstatus": 0,
  "doctype": "Property Setter",
  "doctype_or_field": "DocField",
  "field_name": "additional_discount_account",
  "modified": "2022-10-12 17:35:16.277371",
  "name": "Purchase Invoice-additional_discount_account-hidden",
  "parent": null,
  "parentfield": null,
  "parenttype": null,
  "property": "hidden",
  "property_type": "Check",
  "row_name": null,
  "value": "1"
 },
 {
  "default_value": null,
  "doc_type": "Purchase Invoice",
  "docstatus": 0,
  "doctype": "Property Setter",
  "doctype_or_field": "DocField",
  "field_name": "additional_discount_account",
  "modified": "2022-10-12 17:35:16.287422",
  "name": "Purchase Invoice-additional_discount_account-mandatory_depends_on",
  "parent": null,
  "parentfield": null,
  "parenttype": null,
  "property": "mandatory_depends_on",
  "property_type": "Code",
  "row_name": null,
  "value": ""
 },
 {
  "default_value": null,
  "doc_type": "Item",
  "docstatus": 0,
  "doctype": "Property Setter",
  "doctype_or_field": "DocField",
  "field_name": "default_discount_account",
  "modified": "2022-10-12 17:35:16.298142",
  "name": "Item-default_discount_account-hidden",
  "parent": null,
  "parentfield": null,
  "parenttype": null,
  "property": "hidden",
  "property_type": "Check",
  "row_name": null,
  "value": "1"
 },
 {
  "default_value": null,
  "doc_type": "Item",
  "docstatus": 0,
  "doctype": "Property Setter",
  "doctype_or_field": "DocField",
  "field_name": "naming_series",
  "modified": "2022-10-12 17:35:16.876303",
  "name": "Item-naming_series-reqd",
  "parent": null,
  "parentfield": null,
  "parenttype": null,
  "property": "reqd",
  "property_type": "Check",
  "row_name": null,
  "value": "0"
 },
 {
  "default_value": null,
  "doc_type": "Item",
  "docstatus": 0,
  "doctype": "Property Setter",
  "doctype_or_field": "DocField",
  "field_name": "naming_series",
  "modified": "2022-10-12 17:35:16.908888",
  "name": "Item-naming_series-hidden",
  "parent": null,
  "parentfield": null,
  "parenttype": null,
  "property": "hidden",
  "property_type": "Check",
  "row_name": null,
  "value": "1"
 },
 {
  "default_value": null,
  "doc_type": "Item",
  "docstatus": 0,
  "doctype": "Property Setter",
  "doctype_or_field": "DocField",
  "field_name": "item_code",
  "modified": "2022-10-12 17:35:16.919963",
  "name": "Item-item_code-hidden",
  "parent": null,
  "parentfield": null,
  "parenttype": null,
  "property": "hidden",
  "property_type": "Check",
  "row_name": null,
  "value": "0"
 },
 {
  "default_value": null,
  "doc_type": "Item",
  "docstatus": 0,
  "doctype": "Property Setter",
  "doctype_or_field": "DocField",
  "field_name": "item_code",
  "modified": "2022-10-12 17:35:16.931745",
  "name": "Item-item_code-reqd",
  "parent": null,
  "parentfield": null,
  "parenttype": null,
  "property": "reqd",
  "property_type": "Check",
  "row_name": null,
  "value": "1"
 },
 {
  "default_value": null,
  "doc_type": "Sales Invoice Item",
  "docstatus": 0,
  "doctype": "Property Setter",
  "doctype_or_field": "DocField",
  "field_name": "barcode",
  "modified": "2022-10-12 17:35:16.965223",
  "name": "Sales Invoice Item-barcode-hidden",
  "parent": null,
  "parentfield": null,
  "parenttype": null,
  "property": "hidden",
  "property_type": "Check",
  "row_name": null,
  "value": "1"
 },
 {
  "default_value": null,
  "doc_type": "POS Invoice Item",
  "docstatus": 0,
  "doctype": "Property Setter",
  "doctype_or_field": "DocField",
  "field_name": "barcode",
  "modified": "2022-10-12 17:35:16.983285",
  "name": "POS Invoice Item-barcode-hidden",
  "parent": null,
  "parentfield": null,
  "parenttype": null,
  "property": "hidden",
  "property_type": "Check",
  "row_name": null,
  "value": "1"
 },
 {
  "default_value": null,
  "doc_type": "Job Card",
  "docstatus": 0,
  "doctype": "Property Setter",
  "doctype_or_field": "DocField",
  "field_name": "barcode",
  "modified": "2022-10-12 17:35:16.999134",
  "name": "Job Card-barcode-hidden",
  "parent": null,
  "parentfield": null,
  "parenttype": null,
  "property": "hidden",
  "property_type": "Check",
  "row_name": null,
  "value": "1"
 },
 {
  "default_value": null,
  "doc_type": "Item Barcode",
  "docstatus": 0,
  "doctype": "Property Setter",
  "doctype_or_field": "DocField",
  "field_name": "barcode",
  "modified": "2022-10-12 17:35:17.014447",
  "name": "Item Barcode-barcode-hidden",
  "parent": null,
  "parentfield": null,
  "parenttype": null,
  "property": "hidden",
  "property_type": "Check",
  "row_name": null,
  "value": "1"
 },
 {
  "default_value": null,
  "doc_type": "Stock Entry Detail",
  "docstatus": 0,
  "doctype": "Property Setter",
  "doctype_or_field": "DocField",
  "field_name": "barcode",
  "modified": "2022-10-12 17:35:17.030668",
  "name": "Stock Entry Detail-barcode-hidden",
  "parent": null,
  "parentfield": null,
  "parenttype": null,
  "property": "hidden",
  "property_type": "Check",
  "row_name": null,
  "value": "1"
 },
 {
  "default_value": null,
  "doc_type": "Purchase Receipt Item",
  "docstatus": 0,
  "doctype": "Property Setter",
  "doctype_or_field": "DocField",
  "field_name": "barcode",
  "modified": "2022-10-12 17:35:17.046612",
  "name": "Purchase Receipt Item-barcode-hidden",
  "parent": null,
  "parentfield": null,
  "parenttype": null,
  "property": "hidden",
  "property_type": "Check",
  "row_name": null,
  "value": "1"
 },
 {
  "default_value": null,
  "doc_type": "Delivery Note Item",
  "docstatus": 0,
  "doctype": "Property Setter",
  "doctype_or_field": "DocField",
  "field_name": "barcode",
  "modified": "2022-10-12 17:35:17.062283",
  "name": "Delivery Note Item-barcode-hidden",
  "parent": null,
  "parentfield": null,
  "parenttype": null,
  "property": "hidden",
  "property_type": "Check",
  "row_name": null,
  "value": "1"
 },
 {
  "default_value": null,
  "doc_type": "Clinical Procedure Item",
  "docstatus": 0,
  "doctype": "Property Setter",
  "doctype_or_field": "DocField",
  "field_name": "barcode",
  "modified": "2022-10-12 17:35:17.082528",
  "name": "Clinical Procedure Item-barcode-hidden",
  "parent": null,
  "parentfield": null,
  "parenttype": null,
  "property": "hidden",
  "property_type": "Check",
  "row_name": null,
  "value": "1"
 },
 {
  "default_value": null,
  "doc_type": "Stock Reconciliation Item",
  "docstatus": 0,
  "doctype": "Property Setter",
  "doctype_or_field": "DocField",
  "field_name": "barcode",
  "modified": "2022-10-12 17:35:17.102150",
  "name": "Stock Reconciliation Item-barcode-hidden",
  "parent": null,
  "parentfield": null,
  "parenttype": null,
  "property": "hidden",
  "property_type": "Check",
  "row_name": null,
  "value": "1"
 },
 {
  "default_value": null,
  "doc_type": "Item",
  "docstatus": 0,
  "doctype": "Property Setter",
  "doctype_or_field": "DocField",
  "field_name": "barcodes",
  "modified": "2022-10-12 17:35:17.120489",
  "name": "Item-barcodes-hidden",
  "parent": null,
  "parentfield": null,
  "parenttype": null,
  "property": "hidden",
  "property_type": "Check",
  "row_name": null,
  "value": "1"
 },
 {
  "default_value": null,
  "doc_type": "Sales Order",
  "docstatus": 0,
  "doctype": "Property Setter",
  "doctype_or_field": "DocField",
  "field_name": "scan_barcode",
  "modified": "2022-10-12 17:35:17.149152",
  "name": "Sales Order-scan_barcode-hidden",
  "parent": null,
  "parentfield": null,
  "parenttype": null,
  "property": "hidden",
  "property_type": "Check",
  "row_name": null,
  "value": "1"
 },
 {
  "default_value": null,
  "doc_type": "Material Request",
  "docstatus": 0,
  "doctype": "Property Setter",
  "doctype_or_field": "DocField",
  "field_name": "scan_barcode",
  "modified": "2022-10-12 17:35:17.165372",
  "name": "Material Request-scan_barcode-hidden",
  "parent": null,
  "parentfield": null,
  "parenttype": null,
  "property": "hidden",
  "property_type": "Check",
  "row_name": null,
  "value": "1"
 },
 {
  "default_value": null,
  "doc_type": "Purchase Receipt",
  "docstatus": 0,
  "doctype": "Property Setter",
  "doctype_or_field": "DocField",
  "field_name": "scan_barcode",
  "modified": "2022-10-12 17:35:17.182631",
  "name": "Purchase Receipt-scan_barcode-hidden",
  "parent": null,
  "parentfield": null,
  "parenttype": null,
  "property": "hidden",
  "property_type": "Check",
  "row_name": null,
  "value": "1"
 },
 {
  "default_value": null,
  "doc_type": "Purchase Order",
  "docstatus": 0,
  "doctype": "Property Setter",
  "doctype_or_field": "DocField",
  "field_name": "scan_barcode",
  "modified": "2022-10-12 17:35:17.200372",
  "name": "Purchase Order-scan_barcode-hidden",
  "parent": null,
  "parentfield": null,
  "parenttype": null,
  "property": "hidden",
  "property_type": "Check",
  "row_name": null,
  "value": "1"
 },
 {
  "default_value": null,
  "doc_type": "Sales Invoice",
  "docstatus": 0,
  "doctype": "Property Setter",
  "doctype_or_field": "DocField",
  "field_name": "scan_barcode",
  "modified": "2022-10-12 17:35:17.217045",
  "name": "Sales Invoice-scan_barcode-hidden",
  "parent": null,
  "parentfield": null,
  "parenttype": null,
  "property": "hidden",
  "property_type": "Check",
  "row_name": null,
  "value": "1"
 },
 {
  "default_value": null,
  "doc_type": "Purchase Invoice",
  "docstatus": 0,
  "doctype": "Property Setter",
  "doctype_or_field": "DocField",
  "field_name": "scan_barcode",
  "modified": "2022-10-12 17:35:17.233879",
  "name": "Purchase Invoice-scan_barcode-hidden",
  "parent": null,
  "parentfield": null,
  "parenttype": null,
  "property": "hidden",
  "property_type": "Check",
  "row_name": null,
  "value": "1"
 },
 {
  "default_value": null,
  "doc_type": "POS Invoice",
  "docstatus": 0,
  "doctype": "Property Setter",
  "doctype_or_field": "DocField",
  "field_name": "scan_barcode",
  "modified": "2022-10-12 17:35:17.250847",
  "name": "POS Invoice-scan_barcode-hidden",
  "parent": null,
  "parentfield": null,
  "parenttype": null,
  "property": "hidden",
  "property_type": "Check",
  "row_name": null,
  "value": "1"
 },
 {
  "default_value": null,
  "doc_type": "Stock Entry",
  "docstatus": 0,
  "doctype": "Property Setter",
  "doctype_or_field": "DocField",
  "field_name": "scan_barcode",
  "modified": "2022-10-12 17:35:17.268513",
  "name": "Stock Entry-scan_barcode-hidden",
  "parent": null,
  "parentfield": null,
  "parenttype": null,
  "property": "hidden",
  "property_type": "Check",
  "row_name": null,
  "value": "1"
 },
 {
  "default_value": null,
  "doc_type": "Delivery Note",
  "docstatus": 0,
  "doctype": "Property Setter",
  "doctype_or_field": "DocField",
  "field_name": "scan_barcode",
  "modified": "2022-10-12 17:35:17.285718",
  "name": "Delivery Note-scan_barcode-hidden",
  "parent": null,
  "parentfield": null,
  "parenttype": null,
  "property": "hidden",
  "property_type": "Check",
  "row_name": null,
  "value": "1"
 },
 {
  "default_value": null,
  "doc_type": "Sales Invoice Item",
  "docstatus": 0,
  "doctype": "Property Setter",
  "doctype_or_field": "DocField",
  "field_name": "target_warehouse",
  "modified": "2022-10-12 17:35:17.318837",
  "name": "Sales Invoice Item-target_warehouse-hidden",
  "parent": null,
  "parentfield": null,
  "parenttype": null,
  "property": "hidden",
  "property_type": "Check",
  "row_name": null,
  "value": "1"
 },
 {
  "default_value": null,
  "doc_type": "Delivery Note Item",
  "docstatus": 0,
  "doctype": "Property Setter",
  "doctype_or_field": "DocField",
  "field_name": "target_warehouse",
  "modified": "2022-10-12 17:35:17.331798",
  "name": "Delivery Note Item-target_warehouse-hidden",
  "parent": null,
  "parentfield": null,
  "parenttype": null,
  "property": "hidden",
  "property_type": "Check",
  "row_name": null,
  "value": "1"
 },
 {
  "default_value": null,
  "doc_type": "Purchase Invoice Item",
  "docstatus": 0,
  "doctype": "Property Setter",
  "doctype_or_field": "DocField",
  "field_name": "from_warehouse",
  "modified": "2022-10-12 17:35:17.344928",
  "name": "Purchase Invoice Item-from_warehouse-hidden",
  "parent": null,
  "parentfield": null,
  "parenttype": null,
  "property": "hidden",
  "property_type": "Check",
  "row_name": null,
  "value": "1"
 },
 {
  "default_value": null,
  "doc_type": "Purchase Receipt Item",
  "docstatus": 0,
  "doctype": "Property Setter",
  "doctype_or_field": "DocField",
  "field_name": "from_warehouse",
  "modified": "2022-10-12 17:35:17.356808",
  "name": "Purchase Receipt Item-from_warehouse-hidden",
  "parent": null,
  "parentfield": null,
  "parenttype": null,
  "property": "hidden",
  "property_type": "Check",
  "row_name": null,
  "value": "1"
 },
 {
  "default_value": null,
  "doc_type": "Customer",
  "docstatus": 0,
  "doctype": "Property Setter",
  "doctype_or_field": "DocField",
  "field_name": "naming_series",
  "modified": "2022-10-12 17:35:17.798402",
  "name": "Customer-naming_series-reqd",
  "parent": null,
  "parentfield": null,
  "parenttype": null,
  "property": "reqd",
  "property_type": "Check",
  "row_name": null,
  "value": "0"
 },
 {
  "default_value": null,
  "doc_type": "Customer",
  "docstatus": 0,
  "doctype": "Property Setter",
  "doctype_or_field": "DocField",
  "field_name": "naming_series",
  "modified": "2022-10-12 17:35:17.840272",
  "name": "Customer-naming_series-hidden",
  "parent": null,
  "parentfield": null,
  "parenttype": null,
  "property": "hidden",
  "property_type": "Check",
  "row_name": null,
  "value": "1"
 },
 {
  "default_value": null,
  "doc_type": "Sales Order",
  "docstatus": 0,
  "doctype": "Property Setter",
  "doctype_or_field": "DocField",
  "field_name": "tax_id",
  "modified": "2022-10-12 17:35:17.866113",
  "name": "Sales Order-tax_id-hidden",
  "parent": null,
  "parentfield": null,
  "parenttype": null,
  "property": "hidden",
  "property_type": "Check",
  "row_name": null,
  "value": "0"
 },
 {
  "default_value": null,
  "doc_type": "Sales Order",
  "docstatus": 0,
  "doctype": "Property Setter",
  "doctype_or_field": "DocField",
  "field_name": "tax_id",
  "modified": "2022-10-12 17:35:17.880800",
  "name": "Sales Order-tax_id-print_hide",
  "parent": null,
  "parentfield": null,
  "parenttype": null,
  "property": "print_hide",
  "property_type": "Check",
  "row_name": null,
  "value": "0"
 },
 {
  "default_value": null,
  "doc_type": "Sales Invoice",
  "docstatus": 0,
  "doctype": "Property Setter",
  "doctype_or_field": "DocField",
  "field_name": "tax_id",
  "modified": "2022-10-12 17:35:17.893833",
  "name": "Sales Invoice-tax_id-hidden",
  "parent": null,
  "parentfield": null,
  "parenttype": null,
  "property": "hidden",
  "property_type": "Check",
  "row_name": null,
  "value": "0"
 },
 {
  "default_value": null,
  "doc_type": "Sales Invoice",
  "docstatus": 0,
  "doctype": "Property Setter",
  "doctype_or_field": "DocField",
  "field_name": "tax_id",
  "modified": "2022-10-12 17:35:17.906783",
  "name": "Sales Invoice-tax_id-print_hide",
  "parent": null,
  "parentfield": null,
  "parenttype": null,
  "property": "print_hide",
  "property_type": "Check",
  "row_name": null,
  "value": "0"
 },
 {
  "default_value": null,
  "doc_type": "Delivery Note",
  "docstatus": 0,
  "doctype": "Property Setter",
  "doctype_or_field": "DocField",
  "field_name": "tax_id",
  "modified": "2022-10-12 17:35:17.919672",
  "name": "Delivery Note-tax_id-hidden",
  "parent": null,
  "parentfield": null,
  "parenttype": null,
  "property": "hidden",
  "property_type": "Check",
  "row_name": null,
  "value": "0"
 },
 {
  "default_value": null,
  "doc_type": "Delivery Note",
  "docstatus": 0,
  "doctype": "Property Setter",
  "doctype_or_field": "DocField",
  "field_name": "tax_id",
  "modified": "2022-10-12 17:35:17.931837",
  "name": "Delivery Note-tax_id-print_hide",
  "parent": null,
  "parentfield": null,
  "parenttype": null,
  "property": "print_hide",
  "property_type": "Check",
  "row_name": null,
  "value": "0"
 },
 {
  "default_value": null,
  "doc_type": "Packed Item",
  "docstatus": 0,
  "doctype": "Property Setter",
  "doctype_or_field": "DocField",
  "field_name": "rate",
  "modified": "2022-10-12 17:35:17.943674",
  "name": "Packed Item-rate-read_only",
  "parent": null,
  "parentfield": null,
  "parenttype": null,
  "property": "read_only",
  "property_type": "Check",
  "row_name": null,
  "value": "1"
 },
 {
  "default_value": null,
  "doc_type": "Supplier",
  "docstatus": 0,
  "doctype": "Property Setter",
  "doctype_or_field": "DocField",
  "field_name": "naming_series",
  "modified": "2022-10-12 17:35:18.231927",
  "name": "Supplier-naming_series-reqd",
  "parent": null,
  "parentfield": null,
  "parenttype": null,
  "property": "reqd",
  "property_type": "Check",
  "row_name": null,
  "value": "0"
 },
 {
  "default_value": null,
  "doc_type": "Supplier",
  "docstatus": 0,
  "doctype": "Property Setter",
  "doctype_or_field": "DocField",
  "field_name": "naming_series",
  "modified": "2022-10-12 17:35:18.264175",
  "name": "Supplier-naming_series-hidden",
  "parent": null,
  "parentfield": null,
  "parenttype": null,
  "property": "hidden",
  "property_type": "Check",
  "row_name": null,
  "value": "1"
 },
 {
  "default_value": null,
  "doc_type": "Quotation",
  "docstatus": 0,
  "doctype": "Property Setter",
  "doctype_or_field": "DocField",
  "field_name": "base_rounded_total",
  "modified": "2022-10-12 17:35:18.983637",
  "name": "Quotation-base_rounded_total-hidden",
  "parent": null,
  "parentfield": null,
  "parenttype": null,
  "property": "hidden",
  "property_type": "Check",
  "row_name": null,
  "value": "0"
 },
 {
  "default_value": null,
  "doc_type": "Quotation",
  "docstatus": 0,
  "doctype": "Property Setter",
  "doctype_or_field": "DocField",
  "field_name": "base_rounded_total",
  "modified": "2022-10-12 17:35:19.023141",
  "name": "Quotation-base_rounded_total-print_hide",
  "parent": null,
  "parentfield": null,
  "parenttype": null,
  "property": "print_hide",
  "property_type": "Check",
  "row_name": null,
  "value": "1"
 },
 {
  "default_value": null,
  "doc_type": "Quotation",
  "docstatus": 0,
  "doctype": "Property Setter",
  "doctype_or_field": "DocField",
  "field_name": "rounded_total",
  "modified": "2022-10-12 17:35:19.037761",
  "name": "Quotation-rounded_total-hidden",
  "parent": null,
  "parentfield": null,
  "parenttype": null,
  "property": "hidden",
  "property_type": "Check",
  "row_name": null,
  "value": "0"
 },
 {
  "default_value": null,
  "doc_type": "Quotation",
  "docstatus": 0,
  "doctype": "Property Setter",
  "doctype_or_field": "DocField",
  "field_name": "rounded_total",
  "modified": "2022-10-12 17:35:19.052319",
  "name": "Quotation-rounded_total-print_hide",
  "parent": null,
  "parentfield": null,
  "parenttype": null,
  "property": "print_hide",
  "property_type": "Check",
  "row_name": null,
  "value": "0"
 },
 {
  "default_value": null,
  "doc_type": "Quotation",
  "docstatus": 0,
  "doctype": "Property Setter",
  "doctype_or_field": "DocField",
  "field_name": "disable_rounded_total",
  "modified": "2022-10-12 17:35:19.067174",
  "name": "Quotation-disable_rounded_total-default",
  "parent": null,
  "parentfield": null,
  "parenttype": null,
  "property": "default",
  "property_type": "Text",
  "row_name": null,
  "value": "0"
 },
 {
  "default_value": null,
  "doc_type": "Sales Order",
  "docstatus": 0,
  "doctype": "Property Setter",
  "doctype_or_field": "DocField",
  "field_name": "base_rounded_total",
  "modified": "2022-10-12 17:35:19.080415",
  "name": "Sales Order-base_rounded_total-hidden",
  "parent": null,
  "parentfield": null,
  "parenttype": null,
  "property": "hidden",
  "property_type": "Check",
  "row_name": null,
  "value": "0"
 },
 {
  "default_value": null,
  "doc_type": "Sales Order",
  "docstatus": 0,
  "doctype": "Property Setter",
  "doctype_or_field": "DocField",
  "field_name": "base_rounded_total",
  "modified": "2022-10-12 17:35:19.092302",
  "name": "Sales Order-base_rounded_total-print_hide",
  "parent": null,
  "parentfield": null,
  "parenttype": null,
  "property": "print_hide",
  "property_type": "Check",
  "row_name": null,
  "value": "1"
 },
 {
  "default_value": null,
  "doc_type": "Sales Order",
  "docstatus": 0,
  "doctype": "Property Setter",
  "doctype_or_field": "DocField",
  "field_name": "rounded_total",
  "modified": "2022-10-12 17:35:19.106491",
  "name": "Sales Order-rounded_total-hidden",
  "parent": null,
  "parentfield": null,
  "parenttype": null,
  "property": "hidden",
  "property_type": "Check",
  "row_name": null,
  "value": "0"
 },
 {
  "default_value": null,
  "doc_type": "Sales Order",
  "docstatus": 0,
  "doctype": "Property Setter",
  "doctype_or_field": "DocField",
  "field_name": "rounded_total",
  "modified": "2022-10-12 17:35:19.118447",
  "name": "Sales Order-rounded_total-print_hide",
  "parent": null,
  "parentfield": null,
  "parenttype": null,
  "property": "print_hide",
  "property_type": "Check",
  "row_name": null,
  "value": "0"
 },
 {
  "default_value": null,
  "doc_type": "Sales Order",
  "docstatus": 0,
  "doctype": "Property Setter",
  "doctype_or_field": "DocField",
  "field_name": "disable_rounded_total",
  "modified": "2022-10-12 17:35:19.130407",
  "name": "Sales Order-disable_rounded_total-default",
  "parent": null,
  "parentfield": null,
  "parenttype": null,
  "property": "default",
  "property_type": "Text",
  "row_name": null,
  "value": "0"
 },
 {
  "default_value": null,
  "doc_type": "Sales Invoice",
  "docstatus": 0,
  "doctype": "Property Setter",
  "doctype_or_field": "DocField",
  "field_name": "base_rounded_total",
  "modified": "2022-10-12 17:35:19.142611",
  "name": "Sales Invoice-base_rounded_total-hidden",
  "parent": null,
  "parentfield": null,
  "parenttype": null,
  "property": "hidden",
  "property_type": "Check",
  "row_name": null,
  "value": "0"
 },
 {
  "default_value": null,
  "doc_type": "Sales Invoice",
  "docstatus": 0,
  "doctype": "Property Setter",
  "doctype_or_field": "DocField",
  "field_name": "base_rounded_total",
  "modified": "2022-10-12 17:35:19.154744",
  "name": "Sales Invoice-base_rounded_total-print_hide",
  "parent": null,
  "parentfield": null,
  "parenttype": null,
  "property": "print_hide",
  "property_type": "Check",
  "row_name": null,
  "value": "1"
 },
 {
  "default_value": null,
  "doc_type": "Sales Invoice",
  "docstatus": 0,
  "doctype": "Property Setter",
  "doctype_or_field": "DocField",
  "field_name": "rounded_total",
  "modified": "2022-10-12 17:35:19.169602",
  "name": "Sales Invoice-rounded_total-hidden",
  "parent": null,
  "parentfield": null,
  "parenttype": null,
  "property": "hidden",
  "property_type": "Check",
  "row_name": null,
  "value": "0"
 },
 {
  "default_value": null,
  "doc_type": "Sales Invoice",
  "docstatus": 0,
  "doctype": "Property Setter",
  "doctype_or_field": "DocField",
  "field_name": "rounded_total",
  "modified": "2022-10-12 17:35:19.185433",
  "name": "Sales Invoice-rounded_total-print_hide",
  "parent": null,
  "parentfield": null,
  "parenttype": null,
  "property": "print_hide",
  "property_type": "Check",
  "row_name": null,
  "value": "0"
 },
 {
  "default_value": null,
  "doc_type": "Sales Invoice",
  "docstatus": 0,
  "doctype": "Property Setter",
  "doctype_or_field": "DocField",
  "field_name": "disable_rounded_total",
  "modified": "2022-10-12 17:35:19.200761",
  "name": "Sales Invoice-disable_rounded_total-default",
  "parent": null,
  "parentfield": null,
  "parenttype": null,
  "property": "default",
  "property_type": "Text",
  "row_name": null,
  "value": "0"
 },
 {
  "default_value": null,
  "doc_type": "Delivery Note",
  "docstatus": 0,
  "doctype": "Property Setter",
  "doctype_or_field": "DocField",
  "field_name": "base_rounded_total",
  "modified": "2022-10-12 17:35:19.216774",
  "name": "Delivery Note-base_rounded_total-hidden",
  "parent": null,
  "parentfield": null,
  "parenttype": null,
  "property": "hidden",
  "property_type": "Check",
  "row_name": null,
  "value": "0"
 },
 {
  "default_value": null,
  "doc_type": "Delivery Note",
  "docstatus": 0,
  "doctype": "Property Setter",
  "doctype_or_field": "DocField",
  "field_name": "base_rounded_total",
  "modified": "2022-10-12 17:35:19.230818",
  "name": "Delivery Note-base_rounded_total-print_hide",
  "parent": null,
  "parentfield": null,
  "parenttype": null,
  "property": "print_hide",
  "property_type": "Check",
  "row_name": null,
  "value": "1"
 },
 {
  "default_value": null,
  "doc_type": "Delivery Note",
  "docstatus": 0,
  "doctype": "Property Setter",
  "doctype_or_field": "DocField",
  "field_name": "rounded_total",
  "modified": "2022-10-12 17:35:19.241914",
  "name": "Delivery Note-rounded_total-hidden",
  "parent": null,
  "parentfield": null,
  "parenttype": null,
  "property": "hidden",
  "property_type": "Check",
  "row_name": null,
  "value": "0"
 },
 {
  "default_value": null,
  "doc_type": "Delivery Note",
  "docstatus": 0,
  "doctype": "Property Setter",
  "doctype_or_field": "DocField",
  "field_name": "rounded_total",
  "modified": "2022-10-12 17:35:19.253106",
  "name": "Delivery Note-rounded_total-print_hide",
  "parent": null,
  "parentfield": null,
  "parenttype": null,
  "property": "print_hide",
  "property_type": "Check",
  "row_name": null,
  "value": "0"
 },
 {
  "default_value": null,
  "doc_type": "Delivery Note",
  "docstatus": 0,
  "doctype": "Property Setter",
  "doctype_or_field": "DocField",
  "field_name": "disable_rounded_total",
  "modified": "2022-10-12 17:35:19.264676",
  "name": "Delivery Note-disable_rounded_total-default",
  "parent": null,
  "parentfield": null,
  "parenttype": null,
  "property": "default",
  "property_type": "Text",
  "row_name": null,
  "value": "0"
 },
 {
  "default_value": null,
  "doc_type": "Supplier Quotation",
  "docstatus": 0,
  "doctype": "Property Setter",
  "doctype_or_field": "DocField",
  "field_name": "base_rounded_total",
  "modified": "2022-10-12 17:35:19.275972",
  "name": "Supplier Quotation-base_rounded_total-hidden",
  "parent": null,
  "parentfield": null,
  "parenttype": null,
  "property": "hidden",
  "property_type": "Check",
  "row_name": null,
  "value": "0"
 },
 {
  "default_value": null,
  "doc_type": "Supplier Quotation",
  "docstatus": 0,
  "doctype": "Property Setter",
  "doctype_or_field": "DocField",
  "field_name": "base_rounded_total",
  "modified": "2022-10-12 17:35:19.289610",
  "name": "Supplier Quotation-base_rounded_total-print_hide",
  "parent": null,
  "parentfield": null,
  "parenttype": null,
  "property": "print_hide",
  "property_type": "Check",
  "row_name": null,
  "value": "1"
 },
 {
  "default_value": null,
  "doc_type": "Supplier Quotation",
  "docstatus": 0,
  "doctype": "Property Setter",
  "doctype_or_field": "DocField",
  "field_name": "rounded_total",
  "modified": "2022-10-12 17:35:19.300552",
  "name": "Supplier Quotation-rounded_total-hidden",
  "parent": null,
  "parentfield": null,
  "parenttype": null,
  "property": "hidden",
  "property_type": "Check",
  "row_name": null,
  "value": "0"
 },
 {
  "default_value": null,
  "doc_type": "Supplier Quotation",
  "docstatus": 0,
  "doctype": "Property Setter",
  "doctype_or_field": "DocField",
  "field_name": "rounded_total",
  "modified": "2022-10-12 17:35:19.311625",
  "name": "Supplier Quotation-rounded_total-print_hide",
  "parent": null,
  "parentfield": null,
  "parenttype": null,
  "property": "print_hide",
  "property_type": "Check",
  "row_name": null,
  "value": "0"
 },
 {
  "default_value": null,
  "doc_type": "Supplier Quotation",
  "docstatus": 0,
  "doctype": "Property Setter",
  "doctype_or_field": "DocField",
  "field_name": "disable_rounded_total",
  "modified": "2022-10-12 17:35:19.326018",
  "name": "Supplier Quotation-disable_rounded_total-default",
  "parent": null,
  "parentfield": null,
  "parenttype": null,
  "property": "default",
  "property_type": "Text",
  "row_name": null,
  "value": "0"
 },
 {
  "default_value": null,
  "doc_type": "Purchase Order",
  "docstatus": 0,
  "doctype": "Property Setter",
  "doctype_or_field": "DocField",
  "field_name": "base_rounded_total",
  "modified": "2022-10-12 17:35:19.338480",
  "name": "Purchase Order-base_rounded_total-hidden",
  "parent": null,
  "parentfield": null,
  "parenttype": null,
  "property": "hidden",
  "property_type": "Check",
  "row_name": null,
  "value": "0"
 },
 {
  "default_value": null,
  "doc_type": "Purchase Order",
  "docstatus": 0,
  "doctype": "Property Setter",
  "doctype_or_field": "DocField",
  "field_name": "base_rounded_total",
  "modified": "2022-10-12 17:35:19.354274",
  "name": "Purchase Order-base_rounded_total-print_hide",
  "parent": null,
  "parentfield": null,
  "parenttype": null,
  "property": "print_hide",
  "property_type": "Check",
  "row_name": null,
  "value": "1"
 },
 {
  "default_value": null,
  "doc_type": "Purchase Order",
  "docstatus": 0,
  "doctype": "Property Setter",
  "doctype_or_field": "DocField",
  "field_name": "rounded_total",
  "modified": "2022-10-12 17:35:19.366194",
  "name": "Purchase Order-rounded_total-hidden",
  "parent": null,
  "parentfield": null,
  "parenttype": null,
  "property": "hidden",
  "property_type": "Check",
  "row_name": null,
  "value": "0"
 },
 {
  "default_value": null,
  "doc_type": "Purchase Order",
  "docstatus": 0,
  "doctype": "Property Setter",
  "doctype_or_field": "DocField",
  "field_name": "rounded_total",
  "modified": "2022-10-12 17:35:19.378781",
  "name": "Purchase Order-rounded_total-print_hide",
  "parent": null,
  "parentfield": null,
  "parenttype": null,
  "property": "print_hide",
  "property_type": "Check",
  "row_name": null,
  "value": "0"
 },
 {
  "default_value": null,
  "doc_type": "Purchase Order",
  "docstatus": 0,
  "doctype": "Property Setter",
  "doctype_or_field": "DocField",
  "field_name": "disable_rounded_total",
  "modified": "2022-10-12 17:35:19.390137",
  "name": "Purchase Order-disable_rounded_total-default",
  "parent": null,
  "parentfield": null,
  "parenttype": null,
  "property": "default",
  "property_type": "Text",
  "row_name": null,
  "value": "0"
 },
 {
  "default_value": null,
  "doc_type": "Purchase Invoice",
  "docstatus": 0,
  "doctype": "Property Setter",
  "doctype_or_field": "DocField",
  "field_name": "base_rounded_total",
  "modified": "2022-10-12 17:35:19.400936",
  "name": "Purchase Invoice-base_rounded_total-hidden",
  "parent": null,
  "parentfield": null,
  "parenttype": null,
  "property": "hidden",
  "property_type": "Check",
  "row_name": null,
  "value": "0"
 },
 {
  "default_value": null,
  "doc_type": "Purchase Invoice",
  "docstatus": 0,
  "doctype": "Property Setter",
  "doctype_or_field": "DocField",
  "field_name": "base_rounded_total",
  "modified": "2022-10-12 17:35:19.410694",
  "name": "Purchase Invoice-base_rounded_total-print_hide",
  "parent": null,
  "parentfield": null,
  "parenttype": null,
  "property": "print_hide",
  "property_type": "Check",
  "row_name": null,
  "value": "1"
 },
 {
  "default_value": null,
  "doc_type": "Purchase Invoice",
  "docstatus": 0,
  "doctype": "Property Setter",
  "doctype_or_field": "DocField",
  "field_name": "rounded_total",
  "modified": "2022-10-12 17:35:19.421262",
  "name": "Purchase Invoice-rounded_total-hidden",
  "parent": null,
  "parentfield": null,
  "parenttype": null,
  "property": "hidden",
  "property_type": "Check",
  "row_name": null,
  "value": "0"
 },
 {
  "default_value": null,
  "doc_type": "Purchase Invoice",
  "docstatus": 0,
  "doctype": "Property Setter",
  "doctype_or_field": "DocField",
  "field_name": "rounded_total",
  "modified": "2022-10-12 17:35:19.431827",
  "name": "Purchase Invoice-rounded_total-print_hide",
  "parent": null,
  "parentfield": null,
  "parenttype": null,
  "property": "print_hide",
  "property_type": "Check",
  "row_name": null,
  "value": "0"
 },
 {
  "default_value": null,
  "doc_type": "Purchase Invoice",
  "docstatus": 0,
  "doctype": "Property Setter",
  "doctype_or_field": "DocField",
  "field_name": "disable_rounded_total",
  "modified": "2022-10-12 17:35:19.443366",
  "name": "Purchase Invoice-disable_rounded_total-default",
  "parent": null,
  "parentfield": null,
  "parenttype": null,
  "property": "default",
  "property_type": "Text",
  "row_name": null,
  "value": "0"
 },
 {
  "default_value": null,
  "doc_type": "Purchase Receipt",
  "docstatus": 0,
  "doctype": "Property Setter",
  "doctype_or_field": "DocField",
  "field_name": "base_rounded_total",
  "modified": "2022-10-12 17:35:19.456774",
  "name": "Purchase Receipt-base_rounded_total-hidden",
  "parent": null,
  "parentfield": null,
  "parenttype": null,
  "property": "hidden",
  "property_type": "Check",
  "row_name": null,
  "value": "0"
 },
 {
  "default_value": null,
  "doc_type": "Purchase Receipt",
  "docstatus": 0,
  "doctype": "Property Setter",
  "doctype_or_field": "DocField",
  "field_name": "base_rounded_total",
  "modified": "2022-10-12 17:35:19.467627",
  "name": "Purchase Receipt-base_rounded_total-print_hide",
  "parent": null,
  "parentfield": null,
  "parenttype": null,
  "property": "print_hide",
  "property_type": "Check",
  "row_name": null,
  "value": "1"
 },
 {
  "default_value": null,
  "doc_type": "Purchase Receipt",
  "docstatus": 0,
  "doctype": "Property Setter",
  "doctype_or_field": "DocField",
  "field_name": "rounded_total",
  "modified": "2022-10-12 17:35:19.479258",
  "name": "Purchase Receipt-rounded_total-hidden",
  "parent": null,
  "parentfield": null,
  "parenttype": null,
  "property": "hidden",
  "property_type": "Check",
  "row_name": null,
  "value": "0"
 },
 {
  "default_value": null,
  "doc_type": "Purchase Receipt",
  "docstatus": 0,
  "doctype": "Property Setter",
  "doctype_or_field": "DocField",
  "field_name": "rounded_total",
  "modified": "2022-10-12 17:35:19.490807",
  "name": "Purchase Receipt-rounded_total-print_hide",
  "parent": null,
  "parentfield": null,
  "parenttype": null,
  "property": "print_hide",
  "property_type": "Check",
  "row_name": null,
  "value": "0"
 },
 {
  "default_value": null,
  "doc_type": "Purchase Receipt",
  "docstatus": 0,
  "doctype": "Property Setter",
  "doctype_or_field": "DocField",
  "field_name": "disable_rounded_total",
  "modified": "2022-10-12 17:35:19.503164",
  "name": "Purchase Receipt-disable_rounded_total-default",
  "parent": null,
  "parentfield": null,
  "parenttype": null,
  "property": "default",
  "property_type": "Text",
  "row_name": null,
  "value": "0"
 },
 {
  "default_value": null,
  "doc_type": "Quotation",
  "docstatus": 0,
  "doctype": "Property Setter",
  "doctype_or_field": "DocField",
  "field_name": "in_words",
  "modified": "2022-10-12 17:35:19.516816",
  "name": "Quotation-in_words-hidden",
  "parent": null,
  "parentfield": null,
  "parenttype": null,
  "property": "hidden",
  "property_type": "Check",
  "row_name": null,
  "value": "0"
 },
 {
  "default_value": null,
  "doc_type": "Quotation",
  "docstatus": 0,
  "doctype": "Property Setter",
  "doctype_or_field": "DocField",
  "field_name": "in_words",
  "modified": "2022-10-12 17:35:19.528435",
  "name": "Quotation-in_words-print_hide",
  "parent": null,
  "parentfield": null,
  "parenttype": null,
  "property": "print_hide",
  "property_type": "Check",
  "row_name": null,
  "value": "0"
 },
 {
  "default_value": null,
  "doc_type": "Sales Order",
  "docstatus": 0,
  "doctype": "Property Setter",
  "doctype_or_field": "DocField",
  "field_name": "in_words",
  "modified": "2022-10-12 17:35:19.540411",
  "name": "Sales Order-in_words-hidden",
  "parent": null,
  "parentfield": null,
  "parenttype": null,
  "property": "hidden",
  "property_type": "Check",
  "row_name": null,
  "value": "0"
 },
 {
  "default_value": null,
  "doc_type": "Sales Order",
  "docstatus": 0,
  "doctype": "Property Setter",
  "doctype_or_field": "DocField",
  "field_name": "in_words",
  "modified": "2022-10-12 17:35:19.552927",
  "name": "Sales Order-in_words-print_hide",
  "parent": null,
  "parentfield": null,
  "parenttype": null,
  "property": "print_hide",
  "property_type": "Check",
  "row_name": null,
  "value": "0"
 },
 {
  "default_value": null,
  "doc_type": "Sales Invoice",
  "docstatus": 0,
  "doctype": "Property Setter",
  "doctype_or_field": "DocField",
  "field_name": "in_words",
  "modified": "2022-10-12 17:35:19.565145",
  "name": "Sales Invoice-in_words-hidden",
  "parent": null,
  "parentfield": null,
  "parenttype": null,
  "property": "hidden",
  "property_type": "Check",
  "row_name": null,
  "value": "0"
 },
 {
  "default_value": null,
  "doc_type": "Sales Invoice",
  "docstatus": 0,
  "doctype": "Property Setter",
  "doctype_or_field": "DocField",
  "field_name": "in_words",
  "modified": "2022-10-12 17:35:19.577168",
  "name": "Sales Invoice-in_words-print_hide",
  "parent": null,
  "parentfield": null,
  "parenttype": null,
  "property": "print_hide",
  "property_type": "Check",
  "row_name": null,
  "value": "0"
 },
 {
  "default_value": null,
  "doc_type": "Delivery Note",
  "docstatus": 0,
  "doctype": "Property Setter",
  "doctype_or_field": "DocField",
  "field_name": "in_words",
  "modified": "2022-10-12 17:35:19.589573",
  "name": "Delivery Note-in_words-hidden",
  "parent": null,
  "parentfield": null,
  "parenttype": null,
  "property": "hidden",
  "property_type": "Check",
  "row_name": null,
  "value": "0"
 },
 {
  "default_value": null,
  "doc_type": "Delivery Note",
  "docstatus": 0,
  "doctype": "Property Setter",
  "doctype_or_field": "DocField",
  "field_name": "in_words",
  "modified": "2022-10-12 17:35:19.600865",
  "name": "Delivery Note-in_words-print_hide",
  "parent": null,
  "parentfield": null,
  "parenttype": null,
  "property": "print_hide",
  "property_type": "Check",
  "row_name": null,
  "value": "0"
 },
 {
  "default_value": null,
  "doc_type": "Supplier Quotation",
  "docstatus": 0,
  "doctype": "Property Setter",
  "doctype_or_field": "DocField",
  "field_name": "in_words",
  "modified": "2022-10-12 17:35:19.613018",
  "name": "Supplier Quotation-in_words-hidden",
  "parent": null,
  "parentfield": null,
  "parenttype": null,
  "property": "hidden",
  "property_type": "Check",
  "row_name": null,
  "value": "0"
 },
 {
  "default_value": null,
  "doc_type": "Supplier Quotation",
  "docstatus": 0,
  "doctype": "Property Setter",
  "doctype_or_field": "DocField",
  "field_name": "in_words",
  "modified": "2022-10-12 17:35:19.625072",
  "name": "Supplier Quotation-in_words-print_hide",
  "parent": null,
  "parentfield": null,
  "parenttype": null,
  "property": "print_hide",
  "property_type": "Check",
  "row_name": null,
  "value": "0"
 },
 {
  "default_value": null,
  "doc_type": "Purchase Order",
  "docstatus": 0,
  "doctype": "Property Setter",
  "doctype_or_field": "DocField",
  "field_name": "in_words",
  "modified": "2022-10-12 17:35:19.635525",
  "name": "Purchase Order-in_words-hidden",
  "parent": null,
  "parentfield": null,
  "parenttype": null,
  "property": "hidden",
  "property_type": "Check",
  "row_name": null,
  "value": "0"
 },
 {
  "default_value": null,
  "doc_type": "Purchase Order",
  "docstatus": 0,
  "doctype": "Property Setter",
  "doctype_or_field": "DocField",
  "field_name": "in_words",
  "modified": "2022-10-12 17:35:19.646419",
  "name": "Purchase Order-in_words-print_hide",
  "parent": null,
  "parentfield": null,
  "parenttype": null,
  "property": "print_hide",
  "property_type": "Check",
  "row_name": null,
  "value": "0"
 },
 {
  "default_value": null,
  "doc_type": "Purchase Invoice",
  "docstatus": 0,
  "doctype": "Property Setter",
  "doctype_or_field": "DocField",
  "field_name": "in_words",
  "modified": "2022-10-12 17:35:19.657496",
  "name": "Purchase Invoice-in_words-hidden",
  "parent": null,
  "parentfield": null,
  "parenttype": null,
  "property": "hidden",
  "property_type": "Check",
  "row_name": null,
  "value": "0"
 },
 {
  "default_value": null,
  "doc_type": "Purchase Invoice",
  "docstatus": 0,
  "doctype": "Property Setter",
  "doctype_or_field": "DocField",
  "field_name": "in_words",
  "modified": "2022-10-12 17:35:19.668750",
  "name": "Purchase Invoice-in_words-print_hide",
  "parent": null,
  "parentfield": null,
  "parenttype": null,
  "property": "print_hide",
  "property_type": "Check",
  "row_name": null,
  "value": "0"
 },
 {
  "default_value": null,
  "doc_type": "Purchase Receipt",
  "docstatus": 0,
  "doctype": "Property Setter",
  "doctype_or_field": "DocField",
  "field_name": "in_words",
  "modified": "2022-10-12 17:35:19.680739",
  "name": "Purchase Receipt-in_words-hidden",
  "parent": null,
  "parentfield": null,
  "parenttype": null,
  "property": "hidden",
  "property_type": "Check",
  "row_name": null,
  "value": "0"
 },
 {
  "default_value": null,
  "doc_type": "Purchase Receipt",
  "docstatus": 0,
  "doctype": "Property Setter",
  "doctype_or_field": "DocField",
  "field_name": "in_words",
  "modified": "2022-10-12 17:35:19.721045",
  "name": "Purchase Receipt-in_words-print_hide",
  "parent": null,
  "parentfield": null,
  "parenttype": null,
  "property": "print_hide",
  "property_type": "Check",
  "row_name": null,
  "value": "0"
 },
 {
  "default_value": null,
  "doc_type": "Instructor",
  "docstatus": 0,
  "doctype": "Property Setter",
  "doctype_or_field": "DocField",
  "field_name": "naming_series",
  "modified": "2022-10-12 17:35:20.236050",
  "name": "Instructor-naming_series-hidden",
  "parent": null,
  "parentfield": null,
  "parenttype": null,
  "property": "hidden",
  "property_type": "Check",
  "row_name": null,
  "value": "1"
 },
 {
  "default_value": null,
  "doc_type": "Project",
  "docstatus": 0,
  "doctype": "Property Setter",
  "doctype_or_field": "DocField",
  "field_name": "naming_series",
  "modified": "2022-10-12 17:35:30.942956",
  "name": "Project-naming_series-options",
  "parent": null,
  "parentfield": null,
  "parenttype": null,
  "property": "options",
  "property_type": "Text",
  "row_name": null,
  "value": "PROJ-.####"
 },
 {
  "default_value": null,
  "doc_type": "Expense Claim Detail",
  "docstatus": 0,
  "doctype": "Property Setter",
  "doctype_or_field": "DocField",
  "field_name": "sanctioned_amount",
  "modified": "2022-10-26 11:52:12.275506",
  "name": "Expense Claim Detail-sanctioned_amount-in_list_view",
  "parent": null,
  "parentfield": null,
  "parenttype": null,
  "property": "in_list_view",
  "property_type": "Check",
  "row_name": null,
  "value": "0"
 },
 {
  "default_value": null,
  "doc_type": "Expense Claim Detail",
  "docstatus": 0,
  "doctype": "Property Setter",
  "doctype_or_field": "DocField",
  "field_name": "description",
  "modified": "2022-10-26 11:52:41.314356",
  "name": "Expense Claim Detail-description-in_list_view",
  "parent": null,
  "parentfield": null,
  "parenttype": null,
  "property": "in_list_view",
  "property_type": "Check",
  "row_name": null,
  "value": "0"
 },
 {
  "default_value": null,
  "doc_type": "Employee",
  "docstatus": 0,
  "doctype": "Property Setter",
  "doctype_or_field": "DocField",
  "field_name": "holiday_list",
  "modified": "2022-11-11 09:54:22.425334",
  "name": "Employee-holiday_list-reqd",
  "parent": null,
  "parentfield": null,
  "parenttype": null,
  "property": "reqd",
  "property_type": "Check",
  "row_name": null,
  "value": "1"
 },
 {
  "default_value": null,
  "doc_type": "Employee Checkin",
  "docstatus": 0,
  "doctype": "Property Setter",
  "doctype_or_field": "DocField",
  "field_name": "log_type",
  "modified": "2022-11-11 10:05:54.147432",
  "name": "Employee Checkin-log_type-reqd",
  "parent": null,
  "parentfield": null,
  "parenttype": null,
  "property": "reqd",
  "property_type": "Check",
  "row_name": null,
  "value": "1"
 },
 {
  "default_value": null,
  "doc_type": "Employee Onboarding",
  "docstatus": 0,
  "doctype": "Property Setter",
  "doctype_or_field": "DocField",
  "field_name": "employee_onboarding_template",
  "modified": "2022-11-14 10:36:20.306863",
  "name": "Employee Onboarding-employee_onboarding_template-hidden",
  "parent": null,
  "parentfield": null,
  "parenttype": null,
  "property": "hidden",
  "property_type": "Check",
  "row_name": null,
  "value": "1"
 },
 {
  "default_value": null,
  "doc_type": "Employee Onboarding",
  "docstatus": 0,
  "doctype": "Property Setter",
  "doctype_or_field": "DocField",
  "field_name": "table_for_activity",
  "modified": "2022-11-14 10:36:20.520543",
  "name": "Employee Onboarding-table_for_activity-hidden",
  "parent": null,
  "parentfield": null,
  "parenttype": null,
  "property": "hidden",
  "property_type": "Check",
  "row_name": null,
  "value": "1"
 },
 {
  "default_value": null,
  "doc_type": "Employee Separation",
  "docstatus": 0,
  "doctype": "Property Setter",
  "doctype_or_field": "DocField",
  "field_name": "table_for_activity",
  "modified": "2022-11-14 10:42:57.931110",
  "name": "Employee Separation-table_for_activity-hidden",
  "parent": null,
  "parentfield": null,
  "parenttype": null,
  "property": "hidden",
  "property_type": "Check",
  "row_name": null,
  "value": "1"
 },
 {
  "default_value": null,
  "doc_type": "Employee",
  "docstatus": 0,
  "doctype": "Property Setter",
  "doctype_or_field": "DocField",
  "field_name": "grade",
  "modified": "2022-11-21 10:47:41.669641",
  "name": "Employee-grade-reqd",
  "parent": null,
  "parentfield": null,
  "parenttype": null,
  "property": "reqd",
  "property_type": "Check",
  "row_name": null,
  "value": "1"
 },
 {
  "default_value": null,
  "doc_type": "Salary Structure Assignment",
  "docstatus": 0,
  "doctype": "Property Setter",
  "doctype_or_field": "DocField",
  "field_name": "variable",
  "modified": "2022-11-25 15:52:44.203855",
  "name": "Salary Structure Assignment-variable-hidden",
  "parent": null,
  "parentfield": null,
  "parenttype": null,
  "property": "hidden",
  "property_type": "Check",
  "row_name": null,
  "value": "1"
 },
 {
  "default_value": null,
  "doc_type": "Job Opening",
  "docstatus": 0,
  "doctype": "Property Setter",
  "doctype_or_field": "DocField",
  "field_name": "department",
  "modified": "2022-11-26 11:10:30.133465",
  "name": "Job Opening-department-reqd",
  "parent": null,
  "parentfield": null,
  "parenttype": null,
  "property": "reqd",
  "property_type": "Check",
  "row_name": null,
  "value": "1"
 },
 {
  "default_value": null,
  "doc_type": "Leave Allocation",
  "docstatus": 0,
  "doctype": "Property Setter",
  "doctype_or_field": "DocField",
  "field_name": "new_leaves_allocated",
  "modified": "2022-12-13 10:43:33.631928",
  "name": "Leave Allocation-new_leaves_allocated-precision",
  "parent": null,
  "parentfield": null,
  "parenttype": null,
  "property": "precision",
  "property_type": "Select",
  "row_name": null,
  "value": "2"
 },
 {
  "default_value": null,
  "doc_type": "Leave Allocation",
  "docstatus": 0,
  "doctype": "Property Setter",
  "doctype_or_field": "DocField",
  "field_name": "total_leaves_allocated",
  "modified": "2022-12-13 10:43:33.806802",
  "name": "Leave Allocation-total_leaves_allocated-precision",
  "parent": null,
  "parentfield": null,
  "parenttype": null,
  "property": "precision",
  "property_type": "Select",
  "row_name": null,
  "value": "2"
 },
 {
  "default_value": null,
  "doc_type": "Leave Allocation",
  "docstatus": 0,
  "doctype": "Property Setter",
  "doctype_or_field": "DocField",
  "field_name": "total_leaves_encashed",
  "modified": "2022-12-13 10:43:33.869993",
  "name": "Leave Allocation-total_leaves_encashed-precision",
  "parent": null,
  "parentfield": null,
  "parenttype": null,
  "property": "precision",
  "property_type": "Select",
  "row_name": null,
  "value": "2"
 },
 {
  "default_value": null,
  "doc_type": "Salary Structure Assignment",
  "docstatus": 0,
  "doctype": "Property Setter",
  "doctype_or_field": "DocField",
  "field_name": "base",
  "modified": "2022-12-13 12:26:13.751992",
  "name": "Salary Structure Assignment-base-default",
  "parent": null,
  "parentfield": null,
  "parenttype": null,
  "property": "default",
  "property_type": "Text",
  "row_name": null,
  "value": "0"
 },
 {
  "default_value": null,
  "doc_type": "Salary Structure Assignment",
  "docstatus": 0,
  "doctype": "Property Setter",
  "doctype_or_field": "DocField",
  "field_name": "variable",
  "modified": "2022-12-13 12:26:13.850929",
  "name": "Salary Structure Assignment-variable-default",
  "parent": null,
  "parentfield": null,
  "parenttype": null,
  "property": "default",
  "property_type": "Text",
  "row_name": null,
  "value": "0"
 },
 {
  "default_value": null,
  "doc_type": "Leave Application",
  "docstatus": 0,
  "doctype": "Property Setter",
  "doctype_or_field": "DocType",
  "field_name": null,
  "modified": "2022-12-15 18:10:07.449695",
  "name": "Leave Application-main-max_attachments",
  "parent": null,
  "parentfield": null,
  "parenttype": null,
  "property": "max_attachments",
  "property_type": "Int",
  "row_name": null,
  "value": null
 },
 {
  "default_value": null,
  "doc_type": "Salary Slip",
  "docstatus": 0,
  "doctype": "Property Setter",
  "doctype_or_field": "DocField",
  "field_name": "leave_without_pay",
  "modified": "2022-12-15 18:41:10.152863",
  "name": "Salary Slip-leave_without_pay-precision",
  "parent": null,
  "parentfield": null,
  "parenttype": null,
  "property": "precision",
  "property_type": "Select",
  "row_name": null,
  "value": "2"
 },
 {
  "default_value": null,
  "doc_type": "Salary Slip",
  "docstatus": 0,
  "doctype": "Property Setter",
  "doctype_or_field": "DocField",
  "field_name": "absent_days",
  "modified": "2022-12-15 18:41:10.349621",
  "name": "Salary Slip-absent_days-precision",
  "parent": null,
  "parentfield": null,
  "parenttype": null,
  "property": "precision",
  "property_type": "Select",
  "row_name": null,
  "value": "2"
 },
 {
  "default_value": null,
  "doc_type": "Salary Slip",
  "docstatus": 0,
  "doctype": "Property Setter",
  "doctype_or_field": "DocField",
  "field_name": "payment_days",
  "modified": "2022-12-15 18:41:10.658793",
  "name": "Salary Slip-payment_days-precision",
  "parent": null,
  "parentfield": null,
  "parenttype": null,
  "property": "precision",
  "property_type": "Select",
  "row_name": null,
  "value": "2"
 },
 {
  "default_value": null,
  "doc_type": "Employee Checkin",
  "docstatus": 0,
  "doctype": "Property Setter",
  "doctype_or_field": "DocField",
  "field_name": "time",
  "modified": "2022-12-30 17:20:58.055189",
  "name": "Employee Checkin-time-read_only",
  "parent": null,
  "parentfield": null,
  "parenttype": null,
  "property": "read_only",
  "property_type": "Check",
  "row_name": null,
  "value": "1"
 },
 {
  "default_value": null,
  "doc_type": "Employee Checkin",
  "docstatus": 0,
  "doctype": "Property Setter",
  "doctype_or_field": "DocField",
  "field_name": "device_id",
  "modified": "2022-12-30 17:20:58.239705",
  "name": "Employee Checkin-device_id-fetch_from",
  "parent": null,
  "parentfield": null,
  "parenttype": null,
  "property": "fetch_from",
  "property_type": "Small Text",
  "row_name": null,
  "value": "employee.attendance_device_id"
 },
 {
  "default_value": null,
  "doc_type": "Employee Checkin",
  "docstatus": 0,
  "doctype": "Property Setter",
  "doctype_or_field": "DocField",
  "field_name": "device_id",
  "modified": "2022-12-30 17:20:58.309425",
  "name": "Employee Checkin-device_id-read_only",
  "parent": null,
  "parentfield": null,
  "parenttype": null,
  "property": "read_only",
  "property_type": "Check",
  "row_name": null,
  "value": "1"
 },
 {
  "default_value": null,
  "doc_type": "Employee Checkin",
  "docstatus": 0,
  "doctype": "Property Setter",
  "doctype_or_field": "DocField",
  "field_name": "skip_auto_attendance",
  "modified": "2022-12-30 17:23:28.652743",
  "name": "Employee Checkin-skip_auto_attendance-read_only",
  "parent": null,
  "parentfield": null,
  "parenttype": null,
  "property": "read_only",
  "property_type": "Check",
  "row_name": null,
  "value": "1"
 },
 {
  "default_value": null,
  "doc_type": "Employee Checkin",
  "docstatus": 0,
  "doctype": "Property Setter",
  "doctype_or_field": "DocField",
  "field_name": "log_type",
  "modified": "2022-12-30 18:00:24.164405",
  "name": "Employee Checkin-log_type-read_only",
  "parent": null,
  "parentfield": null,
  "parenttype": null,
  "property": "read_only",
  "property_type": "Check",
  "row_name": null,
  "value": "1"
 },
 {
  "default_value": null,
  "doc_type": "Purchase Receipt",
  "docstatus": 0,
  "doctype": "Property Setter",
  "doctype_or_field": "DocField",
  "field_name": "provisional_expense_account",
  "modified": "2023-01-02 08:57:45.491277",
  "name": "Purchase Receipt-provisional_expense_account-hidden",
  "parent": null,
  "parentfield": null,
  "parenttype": null,
  "property": "hidden",
  "property_type": "Check",
  "row_name": null,
  "value": "1"
 },
 {
  "default_value": null,
  "doc_type": "Salary Slip",
  "docstatus": 0,
  "doctype": "Property Setter",
  "doctype_or_field": "DocField",
  "field_name": "rounded_total",
  "modified": "2023-01-04 10:23:47.952492",
  "name": "Salary Slip-rounded_total-hidden",
  "parent": null,
  "parentfield": null,
  "parenttype": null,
  "property": "hidden",
  "property_type": "Check",
  "row_name": null,
  "value": "0"
 },
 {
  "default_value": null,
  "doc_type": "Salary Slip",
  "docstatus": 0,
  "doctype": "Property Setter",
  "doctype_or_field": "DocField",
  "field_name": "rounded_total",
  "modified": "2023-01-04 10:23:48.037512",
  "name": "Salary Slip-rounded_total-print_hide",
  "parent": null,
  "parentfield": null,
  "parenttype": null,
  "property": "print_hide",
  "property_type": "Check",
  "row_name": null,
  "value": "0"
 }
]