{
 "actions": [],
 "allow_rename": 1,
 "autoname": "format:CA-{YY}-{#####}",
 "creation": "2023-07-13 16:52:55.146932",
 "doctype": "DocType",
 "editable_grid": 1,
 "engine": "InnoDB",
 "field_order": [
  "name_of_the_company",
  "prevdoc_docname",
  "company",
  "c_r_no",
  "data_fsljd",
  "year_of_establishment",
  "legal_status",
  "amended_from",
  "customer_address_section",
  "po_box",
  "country",
  "column_break_szksy",
  "postal_code",
  "city",
  "section_break_mktgh",
  "bldg_no",
  "way_no",
  "locality",
  "contact_person_section",
  "name1",
  "designation",
  "id_lc_no",
  "email",
  "column_break_b8vus",
  "tel",
  "mobile",
  "fax",
  "section_break_axic0",
  "nature_of_business",
  "nature_of_proprietor_partners_directors_section",
  "partner_details",
  "sponsors_detsils_section",
  "sponsor_details",
  "sponsor_fixed_assets",
  "customers_bank_details_section",
  "customers_bank_details",
  "applied_credit_limit_section",
  "applied_credit_limits",
  "associate_companies_section",
  "associate_companies",
  "business_during_last_three_years_section",
  "business_during_last_three_years",
  "credit_enjoyed_from_five_major_vendors_section",
  "credit_enjoyed_from_five_major_vendors",
  "authorised_signatories_to_sign_lpos_section",
  "authorised_signatories_to_sign_lpos",
  "authorised_signatories_to_sign_cheques_section",
  "authorised_signatories_to_sign_cheques",
  "authorised_sign_for_ack_goods",
  "authorised_signatories_for_acknowledging_receipt_of_goods"
 ],
 "fields": [
  {
   "fieldname": "name_of_the_company",
   "fieldtype": "Data",
   "label": "Name of the Company"
  },
  {
   "fieldname": "c_r_no",
   "fieldtype": "Data",
   "label": "C.R. No"
  },
  {
   "fieldname": "year_of_establishment",
   "fieldtype": "Int",
   "label": "Year of Establishment"
  },
  {
   "fieldname": "legal_status",
   "fieldtype": "Data",
   "label": "Legal Status"
  },
  {
   "fieldname": "data_fsljd",
   "fieldtype": "Column Break"
  },
  {
   "fieldname": "amended_from",
   "fieldtype": "Link",
   "label": "Amended From",
   "no_copy": 1,
   "options": "Credit Application",
   "print_hide": 1,
   "read_only": 1
  },
  {
   "fieldname": "po_box",
   "fieldtype": "Data",
   "label": "PO Box"
  },
  {
   "fieldname": "country",
   "fieldtype": "Link",
   "label": "Country",
   "options": "Country"
  },
  {
   "fieldname": "column_break_szksy",
   "fieldtype": "Column Break"
  },
  {
   "fieldname": "postal_code",
   "fieldtype": "Data",
   "label": "Postal Code"
  },
  {
   "fieldname": "city",
   "fieldtype": "Data",
   "label": "City"
  },
  {
   "fieldname": "customer_address_section",
   "fieldtype": "Section Break",
   "label": "Customer Address"
  },
  {
   "fieldname": "section_break_mktgh",
   "fieldtype": "Section Break"
  },
  {
   "fieldname": "bldg_no",
   "fieldtype": "Data",
   "label": "Building No"
  },
  {
   "fieldname": "way_no",
   "fieldtype": "Data",
   "label": "Way No"
  },
  {
   "fieldname": "locality",
   "fieldtype": "Data",
   "label": "Locality"
  },
  {
   "fieldname": "contact_person_section",
   "fieldtype": "Section Break",
   "label": "Contact Person"
  },
  {
   "fieldname": "name1",
   "fieldtype": "Data",
   "label": "Name "
  },
  {
   "fieldname": "designation",
   "fieldtype": "Data",
   "label": "Designation"
  },
  {
   "fieldname": "id_lc_no",
   "fieldtype": "Data",
   "label": "ID/LC No"
  },
  {
   "fieldname": "email",
   "fieldtype": "Data",
   "label": "Email"
  },
  {
   "fieldname": "column_break_b8vus",
   "fieldtype": "Column Break"
  },
  {
   "fieldname": "tel",
   "fieldtype": "Int",
   "label": "Telephone"
  },
  {
   "fieldname": "mobile",
   "fieldtype": "Int",
   "label": "Mobile"
  },
  {
   "fieldname": "fax",
   "fieldtype": "Int",
   "label": "Fax"
  },
  {
   "fieldname": "section_break_axic0",
   "fieldtype": "Section Break"
  },
  {
   "fieldname": "nature_of_business",
   "fieldtype": "Data",
   "label": "Nature of Business"
  },
  {
   "fieldname": "nature_of_proprietor_partners_directors_section",
   "fieldtype": "Section Break",
   "label": "Nature of Proprietor / Partners / Directors"
  },
  {
   "fieldname": "partner_details",
   "fieldtype": "Table",
   "options": "Credit Application Partner Details"
  },
  {
   "fieldname": "sponsors_detsils_section",
   "fieldtype": "Section Break",
   "label": "Sponsor's Detsils"
  },
  {
   "fieldname": "sponsor_details",
   "fieldtype": "Table",
   "options": "Credit Application Sponsor Details"
  },
  {
   "fieldname": "sponsor_fixed_assets",
   "fieldtype": "Data",
   "label": "Sponsor's Fixed Assets"
  },
  {
   "fieldname": "customers_bank_details_section",
   "fieldtype": "Section Break",
   "label": "Customer's Bank Details"
  },
  {
   "fieldname": "customers_bank_details",
   "fieldtype": "Table",
   "options": "Customer Bank Details"
  },
  {
   "fieldname": "applied_credit_limit_section",
   "fieldtype": "Section Break",
   "label": "Applied Credit Limit"
  },
  {
   "fieldname": "applied_credit_limits",
   "fieldtype": "Table",
   "options": "Credit Application Credit Details"
  },
  {
   "fieldname": "associate_companies_section",
   "fieldtype": "Section Break",
   "label": "Associate Companies"
  },
  {
   "fieldname": "associate_companies",
   "fieldtype": "Table",
   "options": "Credit Application Associate Companies Details"
  },
  {
   "fieldname": "business_during_last_three_years_section",
   "fieldtype": "Section Break",
   "label": "Business During Last Three Years"
  },
  {
   "fieldname": "business_during_last_three_years",
   "fieldtype": "Table",
   "options": "Credit Application Business Details"
  },
  {
   "fieldname": "credit_enjoyed_from_five_major_vendors_section",
   "fieldtype": "Section Break",
   "label": "Credit Enjoyed From Five Major Vendors"
  },
  {
   "fieldname": "credit_enjoyed_from_five_major_vendors",
   "fieldtype": "Table",
   "options": "Credit Application Vendor Credit Details"
  },
  {
   "fieldname": "authorised_signatories_to_sign_lpos_section",
   "fieldtype": "Section Break",
   "label": "Authorised Signatories to Sign LPO's"
  },
  {
   "fieldname": "authorised_signatories_to_sign_lpos",
   "fieldtype": "Table",
   "options": "Credit Application Authorised Signatures Details"
  },
  {
   "fieldname": "authorised_signatories_to_sign_cheques_section",
   "fieldtype": "Section Break",
   "label": "Authorised Signatories to Sign CHEQUES"
  },
  {
   "fieldname": "authorised_signatories_to_sign_cheques",
   "fieldtype": "Table",
   "options": "Credit Application Authorised Signatures Details"
  },
  {
   "fieldname": "authorised_sign_for_ack_goods",
   "fieldtype": "Section Break",
   "label": "Authorised Signatories for Acknowledging Receipt of Goods / Materials"
  },
  {
   "fieldname": "authorised_signatories_for_acknowledging_receipt_of_goods",
   "fieldtype": "Table",
   "options": "Credit Application Authorised Signatures Details"
  },
  {
   "fieldname": "company",
   "fieldtype": "Link",
   "label": "Company",
   "options": "Company"
  },
  {
   "fieldname": "prevdoc_docname",
   "fieldtype": "Link",
   "hidden": 1,
   "label": "Quotation",
   "options": "Quotation"
  }
 ],
 "index_web_pages_for_search": 1,
 "is_submittable": 1,
 "links": [],
 "modified": "2023-07-19 15:26:36.595449",
 "modified_by": "Administrator",
 "module": "Al Ansari",
 "name": "Credit Application",
 "owner": "Administrator",
 "permissions": [
  {
   "create": 1,
   "delete": 1,
   "email": 1,
   "export": 1,
   "print": 1,
   "read": 1,
   "report": 1,
   "role": "System Manager",
   "share": 1,
   "write": 1
  }
 ],
 "sort_field": "modified",
 "sort_order": "DESC"
}